image_processing_dp/__init__.py
image_processing_dp/turn/__init__.py
image_processing_dp/turn/combination.py
image_processing_dp/turn/transformation.py
image_processing_dp/utility/__init__.py
image_processing_dp/utility/io.py
image_processing_dp/utility/plot.py
image_processing_dp-0.0.2.dist-info/LICENSE
image_processing_dp-0.0.2.dist-info/METADATA
image_processing_dp-0.0.2.dist-info/WHEEL
image_processing_dp-0.0.2.dist-info/top_level.txt
image_processing_dp-0.0.2.dist-info/RECORD
