Metadata-Version: 2.1
Name: image-processing-dp
Version: 0.0.2
Summary: Pacote para processar imagens usando Skimage
Home-page: https://github.com/DanilloSouza03/Pacote-de-processar-imagens
Author: Danillo Souza Pereira
Requires-Python: >=3.5
License-File: LICENSE
Requires-Dist: matplotlib
Requires-Dist: numpy
Requires-Dist: scikit-image (>=0.16.1)
